conformalopt/__init__.py
conformalopt/data.py
conformalopt/main.py
conformalopt/utils.py
conformalopt-0.1.0.dist-info/METADATA
conformalopt-0.1.0.dist-info/WHEEL
conformalopt-0.1.0.dist-info/top_level.txt
conformalopt-0.1.0.dist-info/RECORD
